dehinter/__init__.py
dehinter/__main__.py
dehinter/bitops.py
dehinter/font.py
dehinter/paths.py
dehinter/system.py
dehinter-4.0.0.dist-info/LICENSE
dehinter-4.0.0.dist-info/METADATA
dehinter-4.0.0.dist-info/WHEEL
dehinter-4.0.0.dist-info/entry_points.txt
dehinter-4.0.0.dist-info/top_level.txt
dehinter-4.0.0.dist-info/RECORD
