Metadata-Version: 2.1
Name: dehinter
Version: 4.0.0
Summary: A tool for the removal of TrueType instruction sets (hints) in fonts
Home-page: https://github.com/source-foundry/dehinter
Author: Source Foundry Authors and Contributors
Author-email: chris@sourcefoundry.org
License: Apache License v2.0
Platform: Any
Classifier: Development Status :: 5 - Production/Stable
Classifier: Environment :: Console
Classifier: Environment :: Other Environment
Classifier: Intended Audience :: Developers
Classifier: Intended Audience :: End Users/Desktop
Classifier: License :: OSI Approved :: Apache Software License
Classifier: Natural Language :: English
Classifier: Operating System :: OS Independent
Classifier: Programming Language :: Python
Classifier: Programming Language :: Python :: 3
Classifier: Programming Language :: Python :: 3.7
Classifier: Programming Language :: Python :: 3.8
Classifier: Programming Language :: Python :: 3.9
Classifier: Programming Language :: Python :: 3.10
Classifier: Topic :: Text Processing :: Fonts
Classifier: Topic :: Multimedia :: Graphics
Classifier: Topic :: Multimedia :: Graphics :: Graphics Conversion
Requires-Python: >=3.7.0
Provides-Extra: dev
Provides-Extra: maintain
License-File: LICENSE
